Metadata-Version: 2.1
Name: chatify
Version: 0.2.1
Summary: A python package that adds a magic command to Jupyter notebooks to enable LLM interactions with code cells.
Home-page: https://github.com/ContextLab/chatify
Author: Contextual Dynamics Lab
Author-email: contextualdynamics@gmail.com
License: MIT license
Keywords: chatify
Classifier: Development Status :: 2 - Pre-Alpha
Classifier: Intended Audience :: Developers
Classifier: License :: OSI Approved :: MIT License
Classifier: Natural Language :: English
Classifier: Programming Language :: Python :: 3
Classifier: Programming Language :: Python :: 3.6
Classifier: Programming Language :: Python :: 3.7
Classifier: Programming Language :: Python :: 3.8
Requires-Python: >=3.6
Provides-Extra: hf
License-File: LICENSE
